pyargument/__init__.py
pyargument/__main__.py
pyargument-0.60.dist-info/licenses/LICENSE
pyargument-0.60.dist-info/METADATA
pyargument-0.60.dist-info/WHEEL
pyargument-0.60.dist-info/top_level.txt
pyargument-0.60.dist-info/RECORD
