Metadata-Version: 2.4
Name: pyargument
Version: 0.60
Summary: A lightweight Python command-line argument parser.
Author-email: Ankush Bhagat <ankushbhagatofficial@gmail.com>
License: MIT
Project-URL: Homepage, https://github.com/ankushbhagats/pyargument
Project-URL: Repository, https://github.com/ankushbhagats/pyargument
Requires-Python: >=3.7
License-File: LICENSE
Dynamic: license-file
